iotccm_rpi/__init__.py
iotccm_rpi/helpers.py
iotccm_rpi/i2clcd.py
iotccm_rpi/version.py
iotccm_rpi/capabilities/__init__.py
iotccm_rpi/capabilities/capabilities.py
iotccm_rpi/capabilities/dht11_capability.py
iotccm_rpi/capabilities/lcd_capability.py
iotccm_rpi/capabilities/motion_capability.py
iotccm_rpi-0.0.1a1.dist-info/LICENSE
iotccm_rpi-0.0.1a1.dist-info/METADATA
iotccm_rpi-0.0.1a1.dist-info/WHEEL
iotccm_rpi-0.0.1a1.dist-info/top_level.txt
iotccm_rpi-0.0.1a1.dist-info/RECORD
